<_templates Include="trucks" />
<SuspensionSetVariants>
	<SuspensionSet
		_template="Normal"
		BrokenWheelDamageMultiplier="2"
		CriticalDamageThreshold="0.5"
		DamageCapacity="180"
		Name="tuz_108_warthog_suspension_default"
	>
		<Suspension 
			Damping="0.6"
			Height="0.08" 
			Strength="0.06" 
			WheelType="front" 
			BrokenSuspensionMax="0.1" 
			SuspensionMin="-0.3" 
		/>
		<Suspension 
			Damping="0.6"
			Height="0.08" 
			Strength="0.08" 
			WheelType="rear" 
			BrokenSuspensionMax="0.2" 
			SuspensionMin="-0.3" 
		/>
		<GameData
			Price="3000"
			UnlockByExploration="false"
			UnlockByRank="1"
		>
			<UiDesc
				UiDesc="UI_SUSPENSION_DEFAULT_DESC"
				UiIcon30x30=""
				UiIcon40x40=""
				UiName="UI_SUSPENSION_DEFAULT_NAME"
			/>
		</GameData>
	</SuspensionSet>
	<SuspensionSet
		_template="High"
		BrokenWheelDamageMultiplier="2"
		CriticalDamageThreshold="0.6"
		DamageCapacity="160"
		Name="tuz_108_warthog_suspension_high"
	>
		<Suspension 
			Damping="0.6"
			Height="0.18" 
			Strength="0.06" 
			WheelType="front" 
			BrokenSuspensionMax="0.1" 
			SuspensionMin="-0.3" 
		/>
		<Suspension 
			Damping="0.6"
			Height="0.18" 
			Strength="0.08" 
			WheelType="rear" 
			BrokenSuspensionMax="0.2" 
			SuspensionMin="-0.3" 
		/>
		<GameData
			Price="6400"
			UnlockByExploration="true"
			UnlockByRank="1"
		>
			<UiDesc
				UiDesc="UI_SUSPENSION_HIGH_DESC"
				UiIcon30x30=""
				UiIcon40x40=""
				UiName="UI_SUSPENSION_HIGH_NAME"
			/>
		</GameData>
	</SuspensionSet>
	<SuspensionSet
		_template="High"
		BrokenWheelDamageMultiplier="2"
		CriticalDamageThreshold="0.6"
		DamageCapacity="160"
		Name="tuz_108_warthog_suspension_high_crane"
	>
		<Suspension 
			Damping="0.06"
			Height="0.18" 
			Strength="0.18" 
			WheelType="front" 
			BrokenSuspensionMax="0.1" 
			SuspensionMin="-0.3" 
		/>
		<Suspension 
			Damping="0.09"
			Height="0.18" 
			Strength="0.16" 
			WheelType="rear" 
			BrokenSuspensionMax="0.2" 
			SuspensionMin="-0.3" 
		/>
		<GameData
			Price="6400"
			UnlockByExploration="true"
			UnlockByRank="1"
		>
			<UiDesc
				UiDesc="[JoAT] Raised (Front Crane)"
				UiIcon30x30=""
				UiIcon40x40=""
				UiName="[JoAT] Raised (Front Crane)"
			/>
		</GameData>
	</SuspensionSet>
</SuspensionSetVariants>
